MANIFEST.in
README
distribute_setup.py
setup.cfg
setup.py
Astropysics.egg-info/PKG-INFO
Astropysics.egg-info/SOURCES.txt
Astropysics.egg-info/dependency_links.txt
Astropysics.egg-info/requires.txt
Astropysics.egg-info/top_level.txt
astropysics/__init__.py
astropysics/ccd.py
astropysics/constants.py
astropysics/coords.py
astropysics/io.py
astropysics/objcat.py
astropysics/obstools.py
astropysics/phot.py
astropysics/plotting.py
astropysics/spec.py
astropysics/utils.py
astropysics/version.py
astropysics/data/JHKbands.dat
astropysics/data/UBVRIbands.dat
astropysics/data/eyeresponse.dat
astropysics/data/galaxy_lines.dat
astropysics/data/iau00a_nutation_ls.tab
astropysics/data/iau00a_nutation_pl.tab
astropysics/data/iau00b_nutation.tab
astropysics/data/obsdb.dat
astropysics/data/obsdb.html
astropysics/data/stellar_lines.dat
astropysics/data/tout
astropysics/data/ugrizbands.dat
astropysics/data/vega_k93.fits.gz
astropysics/data/vega_k93.pydict
astropysics/data/washingtonbands.dat
astropysics/gui/__init__.py
astropysics/gui/fitgui.py
astropysics/gui/spectarget.py
astropysics/gui/spylot.py
astropysics/models/__init__.py
astropysics/models/builtins.py
astropysics/models/core.py
astropysics/models/pca.py
docs/Makefile
docs/conf.py
docs/index.rst
docs/warnings
docs/coremods/ccd.rst
docs/coremods/constants.rst
docs/coremods/coords.rst
docs/coremods/intro.rst
docs/coremods/io.rst
docs/coremods/models.rst
docs/coremods/objcat.rst
docs/coremods/objcat.rst.~1~
docs/coremods/objcat.rst.~2~
docs/coremods/obstools.rst
docs/coremods/phot.rst
docs/coremods/plotting.rst
docs/coremods/spec.rst
docs/coremods/utils.rst
docs/gui/fitgui.rst
docs/gui/intro.rst
docs/gui/spectarget.rst
docs/gui/spylot.rst
scripts/fitsinfo
scripts/spylot