Metadata-Version: 1.1
Name: Astropysics
Version: 0.1.dev-r632
Summary: Astrophysics libraries for Python
Home-page: http://www.physics.uci.edu/~etolleru/software.html#astropysics
Author: Erik Tollerud
Author-email: etolleru@uci.edu
License: Apache License 2.0
Platform: UNKNOWN
Requires: numpy
Requires: scipy
Provides: astropysics
